{
  "branches": [
    {
      "id": "BR001",
      "name": "મુખ્ય કાર્યાલય",
      "code": "BR001",
      "location": "સ્વરગેટ, પુણે",
      "address": "123, શિવાજી રોડ, સ્વરગેટ, પુણે - 411009",
      "manager": "Rahul Joshi",
      "managerId": "staff-008",
      "phone": "+91-20-24451234",
      "email": "ho@apexbank.example",
      "type": "મુખ્ય કાર્યાલય",
      "staffCount": 45,
      "established": "1985-03-15",
      "status": "active"
    },
    {
      "id": "BR002",
      "name": "કોથરુડ શાખા",
      "code": "BR002",
      "location": "કોથરુડ, પુણે",
      "address": "45, કર્વે રોડ, કોથરુડ, પુણે - 411038",
      "manager": "Anjali Desai",
      "managerId": "staff-013",
      "phone": "+91-20-25432345",
      "email": "kothrud@apexbank.example",
      "type": "શાખા",
      "staffCount": 18,
      "established": "1995-06-10",
      "status": "active"
    },
    {
      "id": "BR003",
      "name": "શિવાજીનગર શાખા",
      "code": "BR003",
      "location": "શિવાજીનગર, પુણે",
      "address": "78, ફર્ગ્યુસન કોલેજ રોડ, શિવાજીનગર, પુણે - 411004",
      "manager": "Meena Naik",
      "managerId": "staff-007",
      "phone": "+91-20-25654567",
      "email": "shivajinagar@apexbank.example",
      "type": "શાખા",
      "staffCount": 15,
      "established": "1998-03-20",
      "status": "active"
    },
    {
      "id": "BR004",
      "name": "કેમ્પ શાખા",
      "code": "BR004",
      "location": "કેમ્પ, પુણે",
      "address": "12, મહાત્મા ગાંધી રોડ, કેમ્પ, પુણે - 411001",
      "manager": "Suresh Patil",
      "managerId": "staff-005",
      "phone": "+91-20-26123456",
      "email": "camp@apexbank.example",
      "type": "શાખા",
      "staffCount": 22,
      "established": "1990-11-15",
      "status": "active"
    },
    {
      "id": "BR005",
      "name": "કસાર સાઈ શાખા",
      "code": "BR005",
      "location": "કસાર સાઈ, પુણે",
      "address": "89, સોલાપુર રોડ, કસાર સાઈ, પુણે - 411011",
      "manager": "Deepak Ghorpade",
      "managerId": "staff-009",
      "phone": "+91-20-26345678",
      "email": "kasarsai@apexbank.example",
      "type": "શાખા",
      "staffCount": 12,
      "established": "2005-08-01",
      "status": "active"
    },
    {
      "id": "BR006",
      "name": "ચિંચવડ શાખા",
      "code": "BR006",
      "location": "ચિંચવડ, પુણે",
      "address": "156, મુંબઈ-પુણે રોડ, ચિંચવડ, પુણે - 411033",
      "manager": "Vikram Kulkarni",
      "managerId": "staff-006",
      "phone": "+91-20-27123456",
      "email": "chinchwad@apexbank.example",
      "type": "શાખા",
      "staffCount": 14,
      "established": "2008-04-10",
      "status": "active"
    },
    {
      "id": "BR007",
      "name": "પિંપરી શાખા",
      "code": "BR007",
      "location": "પિંપરી, પુણે",
      "address": "234, પુણે-મુંબઈ રોડ, પિંપરી, પુણે - 411018",
      "manager": "Anjali Desai",
      "managerId": "staff-013",
      "phone": "+91-20-27456789",
      "email": "pimpri@apexbank.example",
      "type": "શાખા",
      "staffCount": 16,
      "established": "2010-06-20",
      "status": "active"
    },
    {
      "id": "BR008",
      "name": "બિબવેવાડી શાખા",
      "code": "BR008",
      "location": "બિબવેવાડી, પુણે",
      "address": "67, બાલાજી નગર, બિબવેવાડી, પુણે - 411037",
      "manager": "Rahul Joshi",
      "managerId": "staff-008",
      "phone": "+91-20-24234567",
      "email": "bibvewadi@apexbank.example",
      "type": "શાખા",
      "staffCount": 10,
      "established": "2012-09-05",
      "status": "active"
    },
    {
      "id": "BR009",
      "name": "કોંધવા શાખા",
      "code": "BR009",
      "location": "કોંધવા, પુણે",
      "address": "91, NIBM રોડ, કોંધવા, પુણે - 411048",
      "manager": "Meena Naik",
      "managerId": "staff-007",
      "phone": "+91-20-26567890",
      "email": "kondhwa@apexbank.example",
      "type": "શાખા",
      "staffCount": 11,
      "established": "2014-02-15",
      "status": "active"
    },
    {
      "id": "BR010",
      "name": "હડપસર શાખા",
      "code": "BR010",
      "location": "હડપસર, પુણે",
      "address": "123, ગાડીતાલ રોડ, હડપસર, પુણે - 411028",
      "manager": "Suresh Patil",
      "managerId": "staff-005",
      "phone": "+91-20-26789012",
      "email": "hadapsar@apexbank.example",
      "type": "શાખા",
      "staffCount": 13,
      "established": "2015-07-01",
      "status": "active"
    },
    {
      "id": "BR011",
      "name": "વિમાન નગર શાખા",
      "code": "BR011",
      "location": "વિમાન નગર, પુણે",
      "address": "45, નગર રોડ, વિમાન નગર, પુણે - 411014",
      "manager": "Deepak Ghorpade",
      "managerId": "staff-009",
      "phone": "+91-20-27012345",
      "email": "vimannagar@apexbank.example",
      "type": "શાખા",
      "staffCount": 12,
      "established": "2017-01-10",
      "status": "active"
    },
    {
      "id": "BR012",
      "name": "વનોવરી શાખા",
      "code": "BR012",
      "location": "વનોવરી, પુણે",
      "address": "78, સાલુંકે વિહાર રોડ, વનોવરી, પુણે - 411040",
      "manager": "Vikram Kulkarni",
      "managerId": "staff-006",
      "phone": "+91-20-26341234",
      "email": "wanowrie@apexbank.example",
      "type": "શાખા",
      "staffCount": 10,
      "established": "2019-05-20",
      "status": "active"
    }
  ],
  "metadata": {
    "totalBranches": 12,
    "totalStaff": 198,
    "coverage": "Pune District",
    "lastUpdated": "2025-02-07"
  }
}
